ci/transparency/types/__init__.py
ci/transparency/types/_version.py
ci/transparency/types/provenance_tag.py
ci/transparency/types/py.typed
ci/transparency/types/series.py
ci/transparency/types/__pycache__/__init__.cpython-311.pyc
ci/transparency/types/__pycache__/_version.cpython-311.pyc
ci/transparency/types/__pycache__/provenance_tag.cpython-311.pyc
ci/transparency/types/__pycache__/series.cpython-311.pyc
civic_transparency_types-0.2.1.dist-info/licenses/LICENSE
civic_transparency_types-0.2.1.dist-info/METADATA
civic_transparency_types-0.2.1.dist-info/WHEEL
civic_transparency_types-0.2.1.dist-info/top_level.txt
civic_transparency_types-0.2.1.dist-info/RECORD
