Metadata-Version: 2.4
Name: civic-transparency-types
Version: 0.2.1
Summary: Typed Python models (Pydantic v2) for the Civic Transparency specification
Author: Civic Interconnect
License-Expression: MIT
Project-URL: Documentation, https://civic-interconnect.github.io/civic-transparency-types/latest/
Project-URL: Homepage, https://github.com/civic-interconnect/civic-transparency-types
Project-URL: Repository, https://github.com/civic-interconnect/civic-transparency-types
Keywords: civic,transparency,jsonschema,specification,types
Classifier: Programming Language :: Python :: 3
Classifier: Programming Language :: Python :: 3 :: Only
Classifier: Programming Language :: Python :: 3.11
Classifier: Topic :: Software Development :: Libraries
Requires-Python: >=3.11
License-File: LICENSE
Requires-Dist: packaging>=24.0
Requires-Dist: pydantic>=2.6
Requires-Dist: civic-transparency-spec<0.3.0,>=0.2.1
Provides-Extra: dev
Requires-Dist: build; extra == "dev"
Requires-Dist: pre-commit; extra == "dev"
Requires-Dist: pytest; extra == "dev"
Requires-Dist: pytest-cov; extra == "dev"
Requires-Dist: ruff; extra == "dev"
Requires-Dist: mkdocs; extra == "dev"
Requires-Dist: mkdocs-git-revision-date-localized-plugin; extra == "dev"
Requires-Dist: mkdocs-include-markdown-plugin; extra == "dev"
Requires-Dist: mkdocs-material; extra == "dev"
Requires-Dist: mkdocs-minify-plugin; extra == "dev"
Requires-Dist: mkdocs-static-i18n; extra == "dev"
Requires-Dist: mkdocstrings[python]; extra == "dev"
Requires-Dist: mike; extra == "dev"
Requires-Dist: jsonschema; extra == "dev"
Requires-Dist: openapi-spec-validator; extra == "dev"
Requires-Dist: datamodel-code-generator; extra == "dev"
Dynamic: license-file
